[
    {
        "WorkPackage": "mouLrEleTQZJFnYCaWYnqKxzNqlxSRsG",
        "ResourceDemand": "OYtddzIdtRKKuFeFTqnKcjyl",
        "Version": "rDZPHDjqKdJMuXMSZfRGedGygrDI",
        "SkillTagDescription": "SkillTagDescription1"
    },
    {
        "WorkPackage": "QBlYOdMGiHaotfDRNRZAaWtEjikSFPfg",
        "ResourceDemand": "GezmxheVFYMsexHxawDAhCHP",
        "Version": "nDkvmeimzxLLVnpoHkgvRJWNEZQq",
        "SkillTagDescription": "SkillTagDescription2"
    },
    {
        "WorkPackage": "fxGxfUPgVsQLsJGRgBUBKZubFgSHGbsS",
        "ResourceDemand": "ajFiljyMtXkZbbfTlJJPjPZB",
        "Version": "WHMyzFXwdXCRDfPSICJNxfnmUUQv",
        "SkillTagDescription": "SkillTagDescription3"
    },
    {
        "WorkPackage": "LRdxNwFZYKgquDRJQtctREQomJlIMZDM",
        "ResourceDemand": "vysbCtivFOnkFfBTrRmmYcFC",
        "Version": "OfXdmTQKoVqzIMSOjooiVLuuJaUr",
        "SkillTagDescription": "SkillTagDescription4"
    },
    {
        "WorkPackage": "EIYWznyQmcNEDOkVBukWHtQmzrXPskiv",
        "ResourceDemand": "qGnhCWHvKFfESarZcuZajVhf",
        "Version": "XmjmKOxIKqAZaEfygPOKcDrgXSqV",
        "SkillTagDescription": "SkillTagDescription5"
    },
    {
        "WorkPackage": "yhIXLOppWPVZvjCzQQwOqihUrAXJxAvy",
        "ResourceDemand": "OhfgkNOZPvXWwPAhTfsbgevh",
        "Version": "buAnpMKrcasmFvTEKmhSAcOStwbK",
        "SkillTagDescription": "SkillTagDescription6"
    },
    {
        "WorkPackage": "ZsAHUnGVLbRhPTAByAZugETclIOjauHr",
        "ResourceDemand": "xLyrbwwaqPTFslKCXxtESJID",
        "Version": "XMtSxZffYBOFYsJmVUPIQjuvqbMD",
        "SkillTagDescription": "SkillTagDescription7"
    },
    {
        "WorkPackage": "LzlNdjFZJMWFLnQvimsflwiuABBykoRH",
        "ResourceDemand": "oQEQnToYwbjohMMShrlxrqxJ",
        "Version": "QOOoUGbpzsvzkSwruZyrSKSnCjgj",
        "SkillTagDescription": "SkillTagDescription8"
    },
    {
        "WorkPackage": "aqHiIcpxZUlFuHUECCTXeizCLOfcsbgr",
        "ResourceDemand": "OoIrVxqffJiFjVjyzdiYmKQr",
        "Version": "CuXzqAgRKnrjKuyEsPTdYNSsZUEL",
        "SkillTagDescription": "SkillTagDescription9"
    },
    {
        "WorkPackage": "udJGnEFrQEBYSKIhEeuBrZVhWxlfjahW",
        "ResourceDemand": "NcSEfnlOqEdDofAlIwJtFLQW",
        "Version": "QYJBorRgACwQlxQYKIFAuZIQxqlU",
        "SkillTagDescription": "SkillTagDescription10"
    },
    {
        "WorkPackage": "wOuDMzHrvukzevNEjlErUbtpUyVWXYoC",
        "ResourceDemand": "mxCcYtoXpxcAjinVXAZsxnir",
        "Version": "yGVwhMZvHcukKlFqfCUbqutjRHBZ",
        "SkillTagDescription": "SkillTagDescription11"
    },
    {
        "WorkPackage": "oqfcHbEfgSRESYhMiUwcRTKEdEGSCVzQ",
        "ResourceDemand": "QGoVDNjIURpkbJMgfBtqjZvb",
        "Version": "QIPBoVYrHeHibEfaegEaBoYUoRbV",
        "SkillTagDescription": "SkillTagDescription12"
    },
    {
        "WorkPackage": "paVRAyHnVWQaRUiiEzhmzIlqdwzDzGry",
        "ResourceDemand": "kAwWIuShAGGmoEClDmITFNVX",
        "Version": "tTRLMvaIWCqPiFqwuQIIVVjKufzY",
        "SkillTagDescription": "SkillTagDescription13"
    },
    {
        "WorkPackage": "QtYnHuhFOKfNtVGeZuANzDjFqSLWOwsR",
        "ResourceDemand": "AJcdhSnzxmRcTolvCUbulaog",
        "Version": "vfIIlpnLsApkGVovGiGsrLcegbqm",
        "SkillTagDescription": "SkillTagDescription14"
    },
    {
        "WorkPackage": "BDcBmrflyaGBYaHBYNNaGomZPvvEjgii",
        "ResourceDemand": "ebDSyFxHElUbbnbEONPDeGOz",
        "Version": "NTwkaFVPuSCtNADfOzbiThetzJkv",
        "SkillTagDescription": "SkillTagDescription15"
    },
    {
        "WorkPackage": "bAbxWcsuezKZakfbSPEnxXZaXvIvmFTY",
        "ResourceDemand": "LrkXFGbmOJHfAguneFrVrzQH",
        "Version": "KXJCQCQWJYvugVgCgEHDzOBUjilj",
        "SkillTagDescription": "SkillTagDescription16"
    },
    {
        "WorkPackage": "tJhFdPZnGRehneWuGDfLznxcbFbGLtoO",
        "ResourceDemand": "jdgIGrVaDfImYkbfgTwjddUT",
        "Version": "BwFBdZIGlWPJOMFsNnIQsTMhdwHt",
        "SkillTagDescription": "SkillTagDescription17"
    },
    {
        "WorkPackage": "gxoiHVaptlKmiPPGKEBKeGIkIpXdhRER",
        "ResourceDemand": "ecMOldoXMeUzXbBnmkcjQhuY",
        "Version": "rsrENZLdTlOLTezCuoAYaaStCCYI",
        "SkillTagDescription": "SkillTagDescription18"
    },
    {
        "WorkPackage": "yfLPNHMRPwfFjdnsZvMmUAZcEmmMdtWW",
        "ResourceDemand": "ypIZUtkxHsmEpAnEIFfTYOQK",
        "Version": "YbCAwdkHOVRNdtEnfSaOvQfnprqx",
        "SkillTagDescription": "SkillTagDescription19"
    },
    {
        "WorkPackage": "TlRTaddWpXnkWqsOEQvNlrojShCcjgpM",
        "ResourceDemand": "wJPnAnHVilJHVNABXSWSrhRP",
        "Version": "icnDwIjGtLstxQzwrciRLDwkWGrC",
        "SkillTagDescription": "SkillTagDescription20"
    }
]